{
  "sprints": [
    {
      "id": "SPRINT-001",
      "committed_points": 16,
      "completed_points": 16,
      "velocity": 16,
      "closed": "2026-07-07",
      "release": "v0.2.0"
    },
    {
      "id": "SPRINT-002",
      "committed_points": 16,
      "completed_points": 16,
      "velocity": 16,
      "closed": "2026-07-07",
      "release": "v0.3.0"
    },
    {
      "id": "SPRINT-003",
      "committed_points": 16,
      "completed_points": 16,
      "velocity": 16,
      "closed": "2026-07-07",
      "release": "v0.4.0"
    },
    {
      "id": "SPRINT-004",
      "committed_points": 25,
      "completed_points": 25,
      "velocity": 16,
      "closed": "2026-07-07",
      "release": "v0.5.0"
    }
  ],
  "average_velocity": 16,
  "note": "Sprint 4 closed at 100% (stretch 25 pts) — platform admin portal, packages APIs, entitlements cache."
}